rich_text_diff/__init__.py
rich_text_diff-0.0.6.dist-info/DESCRIPTION.rst
rich_text_diff-0.0.6.dist-info/METADATA
rich_text_diff-0.0.6.dist-info/RECORD
rich_text_diff-0.0.6.dist-info/WHEEL
rich_text_diff-0.0.6.dist-info/metadata.json
rich_text_diff-0.0.6.dist-info/top_level.txt
