Metadata-Version: 2.0
Name: rich-text-diff
Version: 0.0.6
Summary: support rich text diff
Home-page: https://github.com/c1ay/rich_text_diff
Author: liukai
Author-email: liukai@zhihu.com
License: UNKNOWN
Platform: UNKNOWN
Requires-Python: >=2.7,!=3.0.*,!=3.1.*,!=3.2.*,!=3.3.*,!=3.4.*
Requires-Dist: lxml
Requires-Dist: diff-match-patch
Requires-Dist: bidict
